kanade-0.0.0.dist-info/METADATA
kanade-0.0.0.dist-info/WHEEL
kanade/__init__.py
kanade/py.typed
kanade-0.0.0.dist-info/RECORD
