Metadata-Version: 2.1
Name: kanade
Version: 0.0.0
Summary: Fast, standard-complaint Python type checker build with Rust.
Author-Email: BlueGlassBlock <blueglassblock@outlook.com>
License: MIT
Classifier: Development Status :: 1 - Planning
Classifier: Topic :: Utilities
Classifier: Typing :: Typed
Classifier: Topic :: Software Development :: Libraries
Classifier: Intended Audience :: Developers
Classifier: License :: OSI Approved :: MIT License
Requires-Python: >=3.7
